ecologits/__init__.py
ecologits/_ecologits.py
ecologits/data/electricity_mixes.csv
ecologits/data/models.json
ecologits/electricity_mix_repository.py
ecologits/exceptions.py
ecologits/impacts/__init__.py
ecologits/impacts/dag.py
ecologits/impacts/llm.py
ecologits/impacts/modeling.py
ecologits/log.py
ecologits/model_repository.py
ecologits/py.typed
ecologits/status_messages.py
ecologits/tracers/__init__.py
ecologits/tracers/anthropic_tracer.py
ecologits/tracers/cohere_tracer.py
ecologits/tracers/google_genai_tracer.py
ecologits/tracers/huggingface_tracer.py
ecologits/tracers/litellm_tracer.py
ecologits/tracers/mistralai_tracer.py
ecologits/tracers/openai_tracer.py
ecologits/tracers/utils.py
ecologits/utils/__init__.py
ecologits/utils/opentelemetry.py
ecologits/utils/range_value.py
ecologits-0.9.2.dist-info/METADATA
ecologits-0.9.2.dist-info/WHEEL
ecologits-0.9.2.dist-info/licenses/LICENSE
ecologits-0.9.2.dist-info/RECORD
