Metadata-Version: 2.4
Name: ecologits
Version: 0.9.2
Summary: EcoLogits tracks and estimates the energy consumption and environmental impacts of using generative AI models through APIs.
License-Expression: MPL-2.0
License-File: LICENSE
Author: Samuel Rincé
Author-email: hello@sento.re
Requires-Python: >=3.10,<4
Classifier: License :: OSI Approved :: Mozilla Public License 2.0 (MPL 2.0)
Classifier: Topic :: Internet
Classifier: Topic :: Scientific/Engineering :: Artificial Intelligence
Classifier: Topic :: Software Development :: Libraries :: Python Modules
Classifier: Intended Audience :: Developers
Classifier: Intended Audience :: Information Technology
Classifier: Intended Audience :: Science/Research
Classifier: Intended Audience :: System Administrators
Classifier: Operating System :: MacOS
Classifier: Operating System :: Microsoft :: Windows
Classifier: Operating System :: OS Independent
Classifier: Operating System :: POSIX
Classifier: Operating System :: POSIX :: Linux
Classifier: Programming Language :: Python :: 3
Classifier: Programming Language :: Python :: 3.10
Classifier: Programming Language :: Python :: 3.11
Classifier: Programming Language :: Python :: 3.12
Classifier: Programming Language :: Python :: 3.13
Classifier: Programming Language :: Python :: 3.14
Provides-Extra: anthropic
Provides-Extra: cohere
Provides-Extra: google-genai
Provides-Extra: huggingface-hub
Provides-Extra: litellm
Provides-Extra: mistralai
Provides-Extra: openai
Provides-Extra: opentelemetry
Requires-Dist: aiohttp (>=3.11.12,<4.0.0) ; extra == "huggingface-hub"
Requires-Dist: anthropic (>=0.45.2,<0.46.0) ; extra == "anthropic"
Requires-Dist: cohere (>=5.13.12,<6.0.0) ; extra == "cohere"
Requires-Dist: google-genai (>=1.26.0,<2.0.0) ; extra == "google-genai"
Requires-Dist: huggingface-hub (>=0.28.1,<0.29.0) ; extra == "huggingface-hub"
Requires-Dist: litellm (>=1.60.6,<2.0.0) ; extra == "litellm"
Requires-Dist: minijinja (>=2.7.0,<3.0.0) ; extra == "huggingface-hub"
Requires-Dist: mistralai (>=1.5.0,<2.0.0) ; extra == "mistralai"
Requires-Dist: openai (>=1.61.1,<2.0.0) ; extra == "openai"
Requires-Dist: opentelemetry-api (>=1.32.1,<2.0.0) ; extra == "opentelemetry"
Requires-Dist: opentelemetry-exporter-otlp (>=1.32.1,<2.0.0) ; extra == "opentelemetry"
Requires-Dist: opentelemetry-sdk (>=1.32.1,<2.0.0) ; extra == "opentelemetry"
Requires-Dist: packaging (>=24.2,<25.0)
Requires-Dist: pydantic (>=1.9.0,<3)
Requires-Dist: rapidfuzz (>=3.12.1,<4.0.0) ; extra == "litellm"
Requires-Dist: tiktoken (>=0.8.0,<0.10.0) ; extra == "huggingface-hub"
Requires-Dist: tiktoken (>=0.8.0,<0.10.0) ; extra == "opentelemetry"
Requires-Dist: wrapt (>=1.14.1,<2.0.0)
